myqlm_fermion-1.3.0.dist-info/licenses/LICENSE
qat/fermion/__init__.py
qat/fermion/ansatz_generator.py
qat/fermion/circuits.py
qat/fermion/fermion_algebra.py
qat/fermion/generator_tools.py
qat/fermion/hamiltonians.py
qat/fermion/matchgates.py
qat/fermion/observable_generator.py
qat/fermion/phase_estimation.py
qat/fermion/transforms.py
qat/fermion/trotterisation.py
qat/fermion/util.py
qat/fermion/vqe.py
qat/fermion/chemistry/__init__.py
qat/fermion/chemistry/pyscf_tools.py
qat/fermion/chemistry/qse.py
qat/fermion/chemistry/ucc.py
qat/fermion/chemistry/ucc_deprecated.py
qat/fermion/chemistry/wrapper.py
qat/fermion/naturalgradient/__init__.py
qat/fermion/naturalgradient/auto_derivatives.py
qat/fermion/naturalgradient/custom_gate_set.py
qat/fermion/naturalgradient/expressions.py
qat/fermion/naturalgradient/qfim_plugin.py
qat/generators/hook_vqe.py
qat/plugins/adapt_vqe.py
qat/plugins/hook_natgrad_plugin.py
qat/plugins/multiple_launches_analyzer.py
qat/plugins/sequential_optimization.py
qat/plugins/transform_observable.py
qat/plugins/zero_noise_extrapolator.py
myqlm_fermion-1.3.0.dist-info/METADATA
myqlm_fermion-1.3.0.dist-info/WHEEL
myqlm_fermion-1.3.0.dist-info/top_level.txt
myqlm_fermion-1.3.0.dist-info/RECORD
