Metadata-Version: 2.4
Name: myqlm-fermion
Version: 1.3.0
Summary: myQLM-fermion package
Home-page: https://atos.net/en/lp/myqlm
Author: Atos Quantum Lab
License: Atos myQLM EULA
Project-URL: Documentation, https://myqlm.github.io
Project-URL: Bug Tracker, https://github.com/myQLM/myqlm-issues/issues
Project-URL: Community, https://myqlmworkspace.slack.com
Project-URL: Source code, https://github.com/myQLM/myqlm-fermion
License-File: LICENSE
Requires-Dist: qat-core
Requires-Dist: qat-lang
Requires-Dist: myqlm
Requires-Dist: anytree
Requires-Dist: bitstring
Requires-Dist: numpy~=2.0
Requires-Dist: scipy
Requires-Dist: tqdm
Dynamic: author
Dynamic: description
Dynamic: description-content-type
Dynamic: home-page
Dynamic: license
Dynamic: license-file
Dynamic: project-url
Dynamic: requires-dist
Dynamic: summary
